oktacli/__init__.py
oktacli/__main__.py
oktacli/api.py
oktacli/cli.py
oktacli/exceptions.py
oktacli/okta.py
oktacli/pwgen.py
oktacli/dotted/__init__.py
oktacli/dotted/collection.py
oktacli/dotted/utils.py
okta_cli-18.1.2.dist-info/LICENSE
okta_cli-18.1.2.dist-info/METADATA
okta_cli-18.1.2.dist-info/WHEEL
okta_cli-18.1.2.dist-info/entry_points.txt
okta_cli-18.1.2.dist-info/top_level.txt
okta_cli-18.1.2.dist-info/RECORD
