Metadata-Version: 2.1
Name: okta-cli
Version: 18.1.2
Summary: An Okta command line interface for scripting and quickly performing routine tasks
Author-email: Axel Bock <ab@a3b3.de>
License: MIT License
Project-URL: Homepage, https://github.com/flypenguin/okta-cli
Project-URL: Repository, https://github.com/flypenguin/okta-cli
Keywords: okta,cli
Classifier: License :: OSI Approved :: MIT License
Classifier: Programming Language :: Python
Classifier: Programming Language :: Python :: 3
Classifier: Programming Language :: Python :: 3.7
Classifier: Programming Language :: Python :: 3.8
Classifier: Programming Language :: Python :: 3.9
Classifier: Programming Language :: Python :: 3.10
Classifier: Programming Language :: Python :: Implementation :: CPython
Requires-Python: >=3.7
License-File: LICENSE
Requires-Dist: appdirs ==1.4.4
Requires-Dist: certifi ==2023.7.22
Requires-Dist: charset-normalizer ==3.3.2
Requires-Dist: click ==8.1.7
Requires-Dist: et-xmlfile ==1.1.0
Requires-Dist: idna ==3.4
Requires-Dist: openpyxl ==3.1.2
Requires-Dist: pony ==0.7.17
Requires-Dist: progressbar2 ==4.3.2
Requires-Dist: python-utils ==3.8.1
Requires-Dist: pyyaml ==6.0.1
Requires-Dist: requests ==2.31.0
Requires-Dist: six ==1.16.0
Requires-Dist: typing-extensions ==4.9.0
Requires-Dist: urllib3 ==2.0.7
